mixlight/__init__.py
mixlight/__main__.py
mixlight/entities.yaml
mixlight/hass.service
mixlight/mixlight.service
mixlight/mixlight.yaml
mixlight/mixlight_board.py
mixlight/mixlight_conf.py
mixlight/mixlight_entity.py
mixlight/mixlight_in.py
mixlight/mixlight_node.py
mixlight/mixlight_out.py
mixlight/mixlight_virt.py
mixlight/entities/__init__.py
mixlight/entities/entity_bina.py
mixlight/entities/entity_dimmer.py
mixlight/entities/entity_flux.py
mixlight/entities/entity_humi.py
mixlight/entities/entity_light.py
mixlight/entities/entity_link.py
mixlight/entities/entity_rgb.py
mixlight/entities/entity_switch.py
mixlight/entities/entity_temp.py
mixlight/virtual/__init__.py
mixlight/virtual/virtual_climate.py
mixlight/virtual/virtual_cover.py
mixlight-0.62.dist-info/DESCRIPTION.rst
mixlight-0.62.dist-info/METADATA
mixlight-0.62.dist-info/RECORD
mixlight-0.62.dist-info/WHEEL
mixlight-0.62.dist-info/entry_points.txt
mixlight-0.62.dist-info/metadata.json
mixlight-0.62.dist-info/top_level.txt
