Metadata-Version: 2.0
Name: mixlight
Version: 0.62
Summary: Service for MIXLight RPi shield MQTT integration
Home-page: https://github.com/lmadean/mixlight
Author: Lucian Madean
Author-email: lmadean@gmail.com
License: UNKNOWN
Platform: UNKNOWN
Classifier: Programming Language :: Python :: 3
Classifier: License :: OSI Approved :: MIT License
Requires-Dist: paho-mqtt
Requires-Dist: pip
Requires-Dist: pyserial
Requires-Dist: pyyaml
Requires-Dist: spidev
Requires-Dist: voluptuous
